strongpods/__init__.py
strongpods/core.py
strongpods-2.1.0.dist-info/METADATA
strongpods-2.1.0.dist-info/WHEEL
strongpods-2.1.0.dist-info/licenses/LICENSE.md
strongpods-2.1.0.dist-info/RECORD
