Metadata-Version: 2.3
Name: strongpods
Version: 2.1.0
Summary: A tiny and simple library for Strongly typed Plain Old Data Structures.
Author-email: Tudor Oancea <oancea.tudor@icloud.com>
License: MIT License
License-File: LICENSE.md
Classifier: Development Status :: 4 - Beta
Classifier: Intended Audience :: Developers
Classifier: License :: OSI Approved :: MIT License
Classifier: Programming Language :: Python :: 3
Requires-Python: >=3.9
Requires-Dist: numpy>=1.25
Provides-Extra: test
Requires-Dist: pytest; extra == 'test'
Requires-Dist: pytest-cov; extra == 'test'
